teorver/__init__.py
teorver/combinatorics/__init__.py
teorver/combinatorics/formulas.py
teorver/probability/__init__.py
teorver/probability/basic.py
teorver-0.0.1.dist-info/METADATA
teorver-0.0.1.dist-info/WHEEL
teorver-0.0.1.dist-info/licenses/LICENSE
teorver-0.0.1.dist-info/RECORD
