Metadata-Version: 2.4
Name: teorver
Version: 0.0.1
Summary: Библиотека для комбинаторики и теории вероятностей
Project-URL: Homepage, https://github.com/aminaaszh/laba04
Author: Амина
License-File: LICENSE
Classifier: License :: OSI Approved :: MIT License
Classifier: Operating System :: OS Independent
Classifier: Programming Language :: Python :: 3
Requires-Python: >=3.8
